musicxmatch_api/__init__.py
musicxmatch_api/main.py
musicxmatch_api-1.0.7.dist-info/METADATA
musicxmatch_api-1.0.7.dist-info/WHEEL
musicxmatch_api-1.0.7.dist-info/top_level.txt
musicxmatch_api-1.0.7.dist-info/RECORD
