Metadata-Version: 2.4
Name: musicxmatch_api
Version: 1.0.7
Summary: Extract lyrics from MusicXMatch API, for free.
Home-page: https://github.com/tomchen/example_pypi_package
Author: Roméo Phillips
Author-email: phillipsromeo@gmail.com
Project-URL: Documentation, https://github.com/Strvm/MusicXMatchAPI
Project-URL: Bug Reports, https://github.com/Strvm/MusicXMatchAPI
Project-URL: Source Code, https://github.com/Strvm/MusicXMatchAPI
Keywords: lyrics,songs,music,musicxmatch,api,musicxmatch_api,musicxmatch_api-python
Classifier: Development Status :: 5 - Production/Stable
Classifier: Intended Audience :: Developers
Classifier: Topic :: Software Development :: Build Tools
Classifier: Programming Language :: Python :: 3
Classifier: Programming Language :: Python :: 3.6
Classifier: Programming Language :: Python :: 3.7
Classifier: Programming Language :: Python :: 3.8
Classifier: Programming Language :: Python :: 3.9
Classifier: Programming Language :: Python :: 3 :: Only
Classifier: License :: OSI Approved :: MIT License
Classifier: Operating System :: OS Independent
Requires-Python: >=3.6
Requires-Dist: requests
Requires-Dist: beautifulsoup4
Provides-Extra: dev
Requires-Dist: check-manifest; extra == "dev"
Dynamic: author
Dynamic: author-email
Dynamic: classifier
Dynamic: description
Dynamic: description-content-type
Dynamic: home-page
Dynamic: keywords
Dynamic: project-url
Dynamic: provides-extra
Dynamic: requires-dist
Dynamic: requires-python
Dynamic: summary
